taskmux/__init__.py
taskmux/cli.py
taskmux/config.py
taskmux/daemon.py
taskmux/main.py
taskmux/tmux_manager.py
taskmux/templates/claude.md
taskmux-0.1.0.dist-info/METADATA
taskmux-0.1.0.dist-info/WHEEL
taskmux-0.1.0.dist-info/entry_points.txt
taskmux-0.1.0.dist-info/licenses/LICENSE
taskmux-0.1.0.dist-info/RECORD
