Metadata-Version: 2.4
Name: taskmux
Version: 0.1.0
Summary: Modern tmux development environment manager with real-time health monitoring, auto-restart, and WebSocket API
Project-URL: Homepage, https://github.com/nc9/taskmux
Project-URL: Repository, https://github.com/nc9/taskmux
Project-URL: Issues, https://github.com/nc9/taskmux/issues
Author-email: Nik Cubrilovic <git@nikcub.me>
License: MIT
License-File: LICENSE
Keywords: daemon,development,manager,monitoring,session,terminal,tmux
Classifier: Development Status :: 4 - Beta
Classifier: Environment :: Console
Classifier: Intended Audience :: Developers
Classifier: License :: OSI Approved :: MIT License
Classifier: Operating System :: MacOS
Classifier: Operating System :: POSIX :: Linux
Classifier: Programming Language :: Python :: 3
Classifier: Programming Language :: Python :: 3.8
Classifier: Programming Language :: Python :: 3.9
Classifier: Programming Language :: Python :: 3.10
Classifier: Programming Language :: Python :: 3.11
Classifier: Programming Language :: Python :: 3.12
Classifier: Topic :: Software Development :: Build Tools
Classifier: Topic :: System :: Monitoring
Classifier: Topic :: Terminals
Requires-Python: >=3.8
Requires-Dist: aiofiles>=23.0.0
Requires-Dist: aiohttp>=3.9.0
Requires-Dist: libtmux>=0.37.0
Requires-Dist: rich>=13.0.0
Requires-Dist: typer>=0.12.0
Requires-Dist: watchdog>=3.0.0
Requires-Dist: websockets>=12.0
